[
  {
    "Arrêtez": [
      {
        "LOC": 1
      }
    ]
  },
  {
    "Baley": [
      {
        "PER": 18
      }
    ]
  },
  {
    "Boris": [
      {
        "PER": 1
      }
    ]
  },
  {
    "Daneel": [
      {
        "PER": 10
      }
    ]
  },
  {
    "Elijah": [
      {
        "PER": 1
      },
      {
        "ORG": 1
      }
    ]
  },
  {
    "Lije": [
      {
        "PER": 1
      },
      {
        "ORG": 1
      }
    ]
  },
  {
    "Mondes Extérieurs": [
      {
        "ORG": 1
      }
    ]
  },
  {
    "R. Daneel": [
      {
        "PER": 8
      }
    ]
  },
  {
    "Ville": [
      {
        "LOC": 1
      }
    ]
  },
  {
    "la Ville": [
      {
        "LOC": 1
      }
    ]
  }
]